oteapi/README.md
oteapi/__init__.py
oteapi/settings.py
oteapi/datacache/__init__.py
oteapi/datacache/datacache.py
oteapi/interfaces/__init__.py
oteapi/interfaces/idownloadstrategy.py
oteapi/interfaces/ifilterstrategy.py
oteapi/interfaces/ifunctionstrategy.py
oteapi/interfaces/imappingstrategy.py
oteapi/interfaces/iparsestrategy.py
oteapi/interfaces/iresourcestrategy.py
oteapi/interfaces/itransformationstrategy.py
oteapi/models/__init__.py
oteapi/models/datacacheconfig.py
oteapi/models/filterconfig.py
oteapi/models/functionconfig.py
oteapi/models/genericconfig.py
oteapi/models/mappingconfig.py
oteapi/models/parserconfig.py
oteapi/models/resourceconfig.py
oteapi/models/secretconfig.py
oteapi/models/transformationconfig.py
oteapi/plugins/__init__.py
oteapi/plugins/entry_points.py
oteapi/plugins/factories.py
oteapi/strategies/__init__.py
oteapi/strategies/download/__init__.py
oteapi/strategies/download/file.py
oteapi/strategies/download/https.py
oteapi/strategies/download/sftp.py
oteapi/strategies/filter/__init__.py
oteapi/strategies/filter/crop_filter.py
oteapi/strategies/filter/sql_query_filter.py
oteapi/strategies/mapping/__init__.py
oteapi/strategies/mapping/mapping.py
oteapi/strategies/parse/__init__.py
oteapi/strategies/parse/application_json.py
oteapi/strategies/parse/application_vnd_sqlite.py
oteapi/strategies/parse/excel_xlsx.py
oteapi/strategies/parse/image.py
oteapi/strategies/parse/postgres.py
oteapi/strategies/parse/text_csv.py
oteapi/strategies/resource/__init__.py
oteapi/strategies/resource/resource_url.py
oteapi/strategies/transformation/__init__.py
oteapi/strategies/transformation/celery_remote.py
oteapi/utils/__init__.py
oteapi/utils/config_updater.py
oteapi/utils/paths.py
oteapi_core-1.0.1.dist-info/entry_points.txt
oteapi_core-1.0.1.dist-info/licenses/LICENSE
oteapi_core-1.0.1.dist-info/WHEEL
oteapi_core-1.0.1.dist-info/METADATA
oteapi_core-1.0.1.dist-info/RECORD
