Metadata-Version: 2.4
Name: oteapi-core
Version: 1.0.1
Summary: Open Translation Environment (OTE) API.
Keywords: OTE,OTEAPI
Author-email: SINTEF <Team4.0@SINTEF.no>
Requires-Python: ~=3.10
Classifier: Programming Language :: Python :: 3
Classifier: Programming Language :: Python :: 3.10
Classifier: Programming Language :: Python :: 3.11
Classifier: Programming Language :: Python :: 3.12
Classifier: Programming Language :: Python :: 3.13
Classifier: License :: OSI Approved :: MIT License
License-File: LICENSE
Requires-Dist: diskcache>=5.6.3,<6
Requires-Dist: pydantic~=2.12
Requires-Dist: pydantic-settings~=2.12
Requires-Dist: celery>=5.6.0,<6
Requires-Dist: openpyxl>=3.1.5,<4
Requires-Dist: paramiko<4
Requires-Dist: Pillow>=10.4.0,<13
Requires-Dist: psycopg[binary]>=3.2.6,<4
Requires-Dist: pysftp~=0.2.9
Requires-Dist: requests>=2.32.3,<3
Requires-Dist: oteapi-core[docs, testing] ; extra == "dev"
Requires-Dist: pre-commit~=4.5 ; extra == "dev"
Requires-Dist: mike~=2.1 ; extra == "docs"
Requires-Dist: mkdocs~=1.6 ; extra == "docs"
Requires-Dist: mkdocs-autorefs~=1.4 ; extra == "docs"
Requires-Dist: mkdocs-awesome-pages-plugin~=2.10 ; extra == "docs"
Requires-Dist: mkdocs-material~=9.7 ; extra == "docs"
Requires-Dist: mkdocstrings[python]~=1.0 ; extra == "docs"
Requires-Dist: ase~=3.26 ; extra == "testing"
Requires-Dist: numpy>=1.26,<3 ; extra == "testing"
Requires-Dist: pytest~=9.0 ; extra == "testing"
Requires-Dist: pytest-celery[redis]~=1.2 ; extra == "testing"
Requires-Dist: pytest-cov~=7.0 ; extra == "testing"
Requires-Dist: redis~=7.0 ; extra == "testing"
Requires-Dist: requests-mock~=1.12 ; extra == "testing"
Project-URL: Changelog, https://github.com/EMMC-ASBL/oteapi-core/blob/master/CHANGELOG.md
Project-URL: Documentation, https://EMMC-ASBL.github.io/oteapi-core
Project-URL: Home, https://github.com/EMMC-ASBL/oteapi-core
Project-URL: Issue Tracker, https://github.com/EMMC-ASBL/oteapi-core/issues
Project-URL: Package, https://pypi.org/project/oteapi-core
Project-URL: Source, https://github.com/EMMC-ASBL/oteapi-core
Provides-Extra: dev
Provides-Extra: docs
Provides-Extra: testing
